netwave/__init__.py
netwave/__main__.py
netwave/netwave.py
netwave_camera-0.0.3.dist-info/LICENSE
netwave_camera-0.0.3.dist-info/METADATA
netwave_camera-0.0.3.dist-info/WHEEL
netwave_camera-0.0.3.dist-info/entry_points.txt
netwave_camera-0.0.3.dist-info/top_level.txt
netwave_camera-0.0.3.dist-info/RECORD
