Metadata-Version: 2.1
Name: netwave-camera
Version: 0.0.3
Summary: A Netwave IP camera API
Home-page: https://github.com/TheLogicMaster/Netwave-Camera
Author: Justin Marentette
Author-email: justinmarentette11@gmail.com
License: WTFPL
Keywords: Netwave,Airsonic,Camera
Platform: UNKNOWN
Classifier: Programming Language :: Python :: 3
Classifier: Development Status :: 3 - Alpha
Classifier: Intended Audience :: Developers
Classifier: Operating System :: OS Independent
Classifier: Topic :: Home Automation
Requires-Python: >=3.6
Requires-Dist: requests
